{
  "type": "FeatureCollection",
  "features": [
    {
      "type": "Feature",
      "properties": {
        "name": "Revolt",
        "hours": "10am - 6pm",
        "phone": "1234567890",
        "description": "SB Road Revolt Showroom"
      },
      "geometry": {
        "type": "Point",
        "coordinates": [
          18.527348,
          73.82598
        ]
      }
    },
    {
      "type": "Feature",
      "properties": {
        "name": "Location 2",
        "hours": "9am - 4pm",
        "phone": "(555) 555-9430",
        "description": "Location #2 description"
      },
      "geometry": {
        "type": "Point",
        "coordinates": [
          18.464099,
          73.868411
        ]
      }
    },
    {
      "type": "Feature",
      "properties": {
        "name": "Location 3",
        "hours": "10am - 8pm",
        "phone": "(555) 555-4839",
        "description": "Location #3 description"
      },
      "geometry": {
        "type": "Point",
        "coordinates": [
          73.82598,
          18.527348
        ]
      }
    },
    {
      "type": "Feature",
      "properties": {
        "name": "Location 4",
        "hours": "8am - 5:30pm",
        "phone": "(555) 555-1989",
        "description": "Location #4 description"
      },
      "geometry": {
        "type": "Point",
        "coordinates": [
          -74.000808,
          40.719723
        ]
      }
    },
    {
      "type": "Feature",
      "properties": {
        "name": "Location 5",
        "hours": "9:30am - 6pm",
        "phone": "(555) 555-4345",
        "description": "Location #5 description"
      },
      "geometry": {
        "type": "Point",
        "coordinates": [
          -73.984496,
          40.696141
        ]
      }
    }
  ]
}